gcn/__init__.py
gcn/_version.py
gcn-0.0.1.dist-info/METADATA
gcn-0.0.1.dist-info/WHEEL
gcn-0.0.1.dist-info/top_level.txt
gcn-0.0.1.dist-info/RECORD
